leafsdk-0.3.4.dist-info/METADATA
leafsdk-0.3.4.dist-info/WHEEL
leafsdk-0.3.4.dist-info/entry_points.txt
leafsdk/__init__.py
leafsdk/core/__init__.py
leafsdk/core/gimbal/__init__.py
leafsdk/core/mission/__init__.py
leafsdk/core/mission/condition.py
leafsdk/core/mission/mission_clock.py
leafsdk/core/mission/mission_plan.py
leafsdk/core/mission/mission_plan_step.py
leafsdk/core/mission/trajectory.py
leafsdk/core/utils/__init__.py
leafsdk/core/utils/transform.py
leafsdk/core/vision/__init__.py
leafsdk/core/vision/camera_stabilizer.py
leafsdk/core/vision/vision_landing.py
leafsdk/setup.py
leafsdk/utils/__init__.py
leafsdk/utils/logstyle.py
leafsdk/utils/util.py
leafsdk-0.3.4.dist-info/RECORD
