Metadata-Version: 2.1
Name: LeafSDK
Version: 0.3.4
Summary: SDK for mission planning
Author-Email: Suleyman Yildirim <suleyman.yildirim@droneleaf.io>, Khalil Al Handawi <khalil.alhandawi@droneleaf.io>, Yaser Othman <yaser.othman@droneleaf.io>
License: MIT
Requires-Python: >=3.10
Requires-Dist: networkx>=3.4.2
Requires-Dist: numpy>=2.2.6
Requires-Dist: scipy>=1.15.3
Requires-Dist: pydot>=4.0.1
